rudderstack/analytics/__init__.py
rudderstack/analytics/client.py
rudderstack/analytics/consumer.py
rudderstack/analytics/get_env.py
rudderstack/analytics/request.py
rudderstack/analytics/utils.py
rudderstack/analytics/version.py
rudderstack/analytics/test/__init__.py
rudderstack/analytics/test/test_client.py
rudderstack/analytics/test/test_constants.py
rudderstack/analytics/test/test_consumer.py
rudderstack/analytics/test/test_module.py
rudderstack/analytics/test/test_request.py
rudderstack/analytics/test/test_utils.py
rudder_sdk_python-2.1.3.dist-info/LICENSE.md
rudder_sdk_python-2.1.3.dist-info/METADATA
rudder_sdk_python-2.1.3.dist-info/WHEEL
rudder_sdk_python-2.1.3.dist-info/top_level.txt
rudder_sdk_python-2.1.3.dist-info/RECORD
