Metadata-Version: 2.1
Name: rudder-sdk-python
Version: 2.1.3
Summary: RudderStack is an open-source Segment alternative written in Go, built for the enterprise.
Home-page: https://github.com/rudderlabs/rudder-sdk-python
Author: RudderStack
Author-email: sdk@rudderstack.com
Maintainer: RudderStack
Maintainer-email: sdk@rudderstack.com
License: MIT License
Keywords: rudder,rudderstack,analytics
Classifier: Development Status :: 5 - Production/Stable
Classifier: Intended Audience :: Developers
Classifier: License :: OSI Approved :: MIT License
Classifier: Operating System :: OS Independent
Classifier: Programming Language :: Python
Classifier: Programming Language :: Python :: 3
Classifier: Programming Language :: Python :: 3.8
Classifier: Programming Language :: Python :: 3.9
Classifier: Programming Language :: Python :: 3.10
Classifier: Programming Language :: Python :: 3.11
Classifier: Programming Language :: Python :: 3.12
Classifier: Topic :: Software Development :: Libraries :: Python Modules
Requires-Python: >=3.8.0
License-File: LICENSE.md
Requires-Dist: requests <3.0,>=2.32.3
Requires-Dist: monotonic <2.0,>=1.6
Requires-Dist: backoff <3.0,>=2.2.1
Requires-Dist: python-dateutil <3.0,>=2.2
Requires-Dist: python-dotenv <2.0.0,>=1.0.1
Requires-Dist: deprecation <3.0.0,>=2.1.0
Provides-Extra: test
Requires-Dist: mock ==4.0.3 ; extra == 'test'
Requires-Dist: flake8 ==7.1.0 ; extra == 'test'
